doorbeen/api/__init__.py
doorbeen/api/__main__.py
doorbeen/api/dependencies.py
doorbeen/api/docs/__init__.py
doorbeen/api/docs/main.py
doorbeen/api/docs/meta.py
doorbeen/api/main.py
doorbeen/api/routers/__init__.py
doorbeen/api/routers/agents.py
doorbeen/api/routers/assistants.py
doorbeen/api/routers/samples.py
doorbeen/api/routers/validators.py
doorbeen/api/schemas/__init__.py
doorbeen/api/schemas/requests/__init__.py
doorbeen/api/schemas/requests/assistants.py
doorbeen/api/schemas/response/__init__.py
doorbeen/api/schemas/response/validators.py
doorbeen/api/static/redoc.standalone.js
doorbeen/api/static/swagger-ui-bundle.js
doorbeen/api/static/swagger-ui.css
doorbeen/api/utils/__init__.py
doorbeen/api/utils/cookies.py
doorbeen/api/utils/errors/__init__.py
doorbeen/api/utils/errors/generate.py
doorbeen/api/utils/exceptions/__init__.py
doorbeen/api/utils/exceptions/validation.py
doorbeen/api/utils/modifiers/__init__.py
doorbeen/api/utils/modifiers/dictionaries.py
doorbeen/api/utils/sockets/__init__.py
doorbeen/api/utils/sockets/common.py
doorbeen/api/workflow.png
doorbeen/core/README.MD
doorbeen/core/__init__.py
doorbeen/core/agents/__init__.py
doorbeen/core/agents/prompts/__init__.py
doorbeen/core/agents/prompts/sql.py
doorbeen/core/agents/router.py
doorbeen/core/agents/sql.py
doorbeen/core/agents/tools/__init__.py
doorbeen/core/agents/tools/parsers/__init__.py
doorbeen/core/agents/tools/parsers/chunk.py
doorbeen/core/assistants/__init__.py
doorbeen/core/assistants/analysis/__init__.py
doorbeen/core/assistants/analysis/grades.py
doorbeen/core/assistants/analysis/sql/__init__.py
doorbeen/core/assistants/analysis/sql/nodes/__init__.py
doorbeen/core/assistants/analysis/sql/nodes/conditionals/__init__.py
doorbeen/core/assistants/analysis/sql/nodes/conditionals/determine.py
doorbeen/core/assistants/analysis/sql/nodes/conditionals/enrich.py
doorbeen/core/assistants/analysis/sql/nodes/conditionals/qn_qa.py
doorbeen/core/assistants/analysis/sql/nodes/entry.py
doorbeen-0.0.1.dist-info/LICENSE
doorbeen-0.0.1.dist-info/METADATA
doorbeen-0.0.1.dist-info/WHEEL
doorbeen-0.0.1.dist-info/RECORD
