Metadata-Version: 2.1
Name: doorbeen
Version: 0.0.1
Summary: Framework to connect LLMs to Internal Databases(SQL and NoSQL)
Home-page: https://jointelescope.com
Author: Telescope
Author-email: info@jointelescope.com
Requires-Python: >=3.12,<3.13
Classifier: License :: OSI Approved :: MIT License
Classifier: Operating System :: OS Independent
Classifier: Programming Language :: Python :: 3
Requires-Dist: clerk-backend-api (>=2.0.0,<3.0.0)
Requires-Dist: deprecated (>=1.2.18,<2.0.0)
Requires-Dist: fastapi-cache2 (>=0.2.1,<0.3.0)
Requires-Dist: fastapi[all] (==0.115.12)
Requires-Dist: google-cloud-bigquery-storage (>=2.30.0,<3.0.0)
Requires-Dist: httpx (>=0.28.1,<0.29.0)
Requires-Dist: kaggle (>=1.6.14,<2.0.0)
Requires-Dist: langchain (==0.3.22)
Requires-Dist: langchain-anthropic (>=0.3.10,<0.4.0)
Requires-Dist: langchain-community (==0.3.20)
Requires-Dist: langchain-experimental (==0.3.4)
Requires-Dist: langchain-google-genai (==2.1.2)
Requires-Dist: langchain-ollama (==0.3.0)
Requires-Dist: langchain-openai (==0.3.11)
Requires-Dist: langgraph (>=0.3.18,<0.4.0)
Requires-Dist: langgraph-checkpoint-postgres (>=2.0.1,<3.0.0)
Requires-Dist: openai (==1.69.0)
Requires-Dist: psycopg-binary (>=3.1.18,<4.0.0)
Requires-Dist: psycopg-pool (>=3.2.3,<4.0.0)
Requires-Dist: psycopg[binary,pool] (>=3.2.3,<4.0.0)
Requires-Dist: pydantic (==2.11.1)
Requires-Dist: pymongo (>=4.6.3,<5.0.0)
Requires-Dist: pymysql (>=1.1.1,<2.0.0)
Requires-Dist: pytz (>=2024.1,<2025.0)
Requires-Dist: scalar-fastapi (>=1.0.3,<2.0.0)
Requires-Dist: secweb (>=1.9.1,<2.0.0)
Requires-Dist: sqlalchemy (==2.0.40)
Requires-Dist: sqlalchemy-bigquery[bqstorage] (>=1.13.0,<2.0.0)
Requires-Dist: uvicorn[standard] (>=0.34.0,<0.35.0)
Project-URL: Documentation, https://github.com/TelescopeAI/doorbeen
Project-URL: Repository, https://github.com/TelescopeAI/doorbeen
